odoo9_addon_account_due_list_days_overdue-9.0.0.1.0.99.dev1-py2.7-nspkg.pth
odoo9_addon_account_due_list_days_overdue-9.0.0.1.0.99.dev1.dist-info/DESCRIPTION.rst
odoo9_addon_account_due_list_days_overdue-9.0.0.1.0.99.dev1.dist-info/METADATA
odoo9_addon_account_due_list_days_overdue-9.0.0.1.0.99.dev1.dist-info/RECORD
odoo9_addon_account_due_list_days_overdue-9.0.0.1.0.99.dev1.dist-info/WHEEL
odoo9_addon_account_due_list_days_overdue-9.0.0.1.0.99.dev1.dist-info/metadata.json
odoo9_addon_account_due_list_days_overdue-9.0.0.1.0.99.dev1.dist-info/namespace_packages.txt
odoo9_addon_account_due_list_days_overdue-9.0.0.1.0.99.dev1.dist-info/top_level.txt
odoo_addons/account_due_list_days_overdue/README.rst
odoo_addons/account_due_list_days_overdue/__init__.py
odoo_addons/account_due_list_days_overdue/__openerp__.py
odoo_addons/account_due_list_days_overdue/demo/account_overdue_term_demo.xml
odoo_addons/account_due_list_days_overdue/i18n/am.po
odoo_addons/account_due_list_days_overdue/i18n/ar.po
odoo_addons/account_due_list_days_overdue/i18n/bg.po
odoo_addons/account_due_list_days_overdue/i18n/bs.po
odoo_addons/account_due_list_days_overdue/i18n/ca.po
odoo_addons/account_due_list_days_overdue/i18n/cs.po
odoo_addons/account_due_list_days_overdue/i18n/da.po
odoo_addons/account_due_list_days_overdue/i18n/de.po
odoo_addons/account_due_list_days_overdue/i18n/el_GR.po
odoo_addons/account_due_list_days_overdue/i18n/en_GB.po
odoo_addons/account_due_list_days_overdue/i18n/es.po
odoo_addons/account_due_list_days_overdue/i18n/es_AR.po
odoo_addons/account_due_list_days_overdue/i18n/es_CL.po
odoo_addons/account_due_list_days_overdue/i18n/es_CO.po
odoo_addons/account_due_list_days_overdue/i18n/es_CR.po
odoo_addons/account_due_list_days_overdue/i18n/es_DO.po
odoo_addons/account_due_list_days_overdue/i18n/es_EC.po
odoo_addons/account_due_list_days_overdue/i18n/es_ES.po
odoo_addons/account_due_list_days_overdue/i18n/es_MX.po
odoo_addons/account_due_list_days_overdue/i18n/es_PE.po
odoo_addons/account_due_list_days_overdue/i18n/es_PY.po
odoo_addons/account_due_list_days_overdue/i18n/es_VE.po
odoo_addons/account_due_list_days_overdue/i18n/et.po
odoo_addons/account_due_list_days_overdue/i18n/eu.po
odoo_addons/account_due_list_days_overdue/i18n/fa.po
odoo_addons/account_due_list_days_overdue/i18n/fi.po
odoo_addons/account_due_list_days_overdue/i18n/fr.po
odoo_addons/account_due_list_days_overdue/i18n/fr_CA.po
odoo_addons/account_due_list_days_overdue/i18n/fr_CH.po
odoo_addons/account_due_list_days_overdue/i18n/gl.po
