Metadata-Version: 2.0
Name: odoo9-addon-account-due-list-days-overdue
Version: 9.0.0.1.0.99.dev1
Summary: Payments Due list days overdue
Home-page: https://github.com/OCA/account-payment
Author: Odoo Community Association (OCA), Eficent
Author-email: support@odoo-community.org
License: AGPL-3
Platform: UNKNOWN
Classifier: Programming Language :: Python :: 2.7
Classifier: Framework :: Odoo
Classifier: License :: OSI Approved :: GNU Affero General Public License v3
Requires-Dist: odoo (<9.1a,>=9.0a)
Requires-Dist: odoo9-addon-account-due-list
